soham/__init__.py
soham-0.0.3.dist-info/METADATA
soham-0.0.3.dist-info/WHEEL
soham-0.0.3.dist-info/licenses/LICENSE
soham-0.0.3.dist-info/RECORD
