Metadata-Version: 2.4
Name: soham
Version: 0.0.3
Summary: A multiagent system that can do multiple jobs at once
License-File: LICENSE
Requires-Python: >=3.12
